{
  "id": "colesmcintosh-numpy",
  "name": "NumPy",
  "provider": "Cole McIntosh",
  "description": "Provides NumPy-based mathematical operations and statistical analysis tools for advanced numerical computations, data...",
  "classification": "community",
  "weekly_metric": null,
  "release_date": "Mar 4, 2025",
  "url": "https://www.pulsemcp.com/servers/colesmcintosh-numpy",
  "source_url": null,
  "categories": [],
  "tags": [],
  "last_updated": null,
  "scraped_at": "2025-11-17T03:45:10.859924",
  "metadata": {}
}