{
  "id": "enkhbold470-bci",
  "name": "BCI-MCP (Brain-Computer Interface)",
  "provider": "enkhbold470",
  "description": "Enables AI systems to receive and process neural signals from multiple EEG devices through real-time signal...",
  "classification": "community",
  "weekly_metric": null,
  "release_date": "Mar 23, 2025",
  "url": "https://www.pulsemcp.com/servers/enkhbold470-bci",
  "source_url": null,
  "categories": [],
  "tags": [],
  "last_updated": null,
  "scraped_at": "2025-11-17T03:44:14.318720",
  "metadata": {}
}