{
  "id": "fred-macroeconomic-data",
  "name": "FRED Macroeconomic Data",
  "provider": "Son Hung Nguyen",
  "description": "Connects to the FRED API to retrieve real-time economic data series including GDP, employment statistics, inflation...",
  "classification": "community",
  "weekly_metric": null,
  "release_date": "Apr 6, 2025",
  "url": "https://www.pulsemcp.com/servers/fred-macroeconomic-data",
  "source_url": null,
  "categories": [],
  "tags": [],
  "last_updated": null,
  "scraped_at": "2025-11-17T03:46:10.308102",
  "metadata": {}
}