{
  "id": "gaplydev-coingecko",
  "name": "CoinGecko",
  "provider": "GaplyDev01",
  "description": "Integrates with CoinGecko's cryptocurrency API to provide real-time market data, pricing information, and detailed...",
  "classification": "community",
  "weekly_metric": null,
  "release_date": "Mar 21, 2025",
  "url": "https://www.pulsemcp.com/servers/gaplydev-coingecko",
  "source_url": null,
  "categories": [],
  "tags": [],
  "last_updated": null,
  "scraped_at": "2025-11-17T03:45:37.009686",
  "metadata": {}
}