{
  "id": "guoling2008-postgres",
  "name": "PostgreSQL",
  "provider": "guoling2008",
  "description": "Enables secure interaction with PostgreSQL databases for schema management and CRUD operations with safety features...",
  "classification": "community",
  "weekly_metric": null,
  "release_date": "Mar 24, 2025",
  "url": "https://www.pulsemcp.com/servers/guoling2008-postgres",
  "source_url": null,
  "categories": [],
  "tags": [],
  "last_updated": null,
  "scraped_at": "2025-11-17T03:46:14.971486",
  "metadata": {}
}