{
  "id": "juanyin1-database-connector",
  "name": "Database Connector",
  "provider": "JuanYin1",
  "description": "Provides multi-database connectivity for SQLite, PostgreSQL, MySQL, and SQL Server through unified adapters that...",
  "classification": "community",
  "weekly_metric": null,
  "release_date": "Jun 10, 2025",
  "url": "https://www.pulsemcp.com/servers/juanyin1-database-connector",
  "source_url": null,
  "categories": [],
  "tags": [],
  "last_updated": null,
  "scraped_at": "2025-11-17T03:46:45.521807",
  "metadata": {}
}