{
  "id": "kingdomseed-structured-workflow",
  "name": "Structured Workflow",
  "provider": "kingdomseed",
  "description": "Provides structured workflow guidance for disciplined software engineering practices through four specialized...",
  "classification": "community",
  "weekly_metric": null,
  "release_date": "Jul 4, 2025",
  "url": "https://www.pulsemcp.com/servers/kingdomseed-structured-workflow",
  "source_url": null,
  "categories": [],
  "tags": [],
  "last_updated": null,
  "scraped_at": "2025-11-17T03:46:54.087485",
  "metadata": {}
}