{
  "id": "lkm1developer-apollo-io",
  "name": "Apollo.io",
  "provider": "Lakhvinder Singh",
  "description": "Integrates with Apollo.io's API to enable access to sales intelligence data, including contact enrichment, company...",
  "classification": "community",
  "weekly_metric": null,
  "release_date": "Apr 14, 2025",
  "url": "https://www.pulsemcp.com/servers/lkm1developer-apollo-io",
  "source_url": null,
  "categories": [],
  "tags": [],
  "last_updated": null,
  "scraped_at": "2025-11-17T03:46:19.245619",
  "metadata": {}
}