{
  "id": "octagonai-deep-research",
  "name": "Octagon Deep Research",
  "provider": "Octagon AI",
  "description": "Integrates with Octagon API to provide multi-source data aggregation, web scraping, academic research synthesis,...",
  "classification": "community",
  "weekly_metric": {
    "type": "downloads",
    "value": 19
  },
  "release_date": "Jun 4, 2025",
  "url": "https://www.pulsemcp.com/servers/octagonai-deep-research",
  "source_url": null,
  "categories": [],
  "tags": [],
  "last_updated": null,
  "scraped_at": "2025-11-17T03:43:25.897095",
  "metadata": {}
}