{
  "id": "runreal-unreal-engine",
  "name": "Unreal Engine",
  "provider": "runreal",
  "description": "Integrates with Unreal Engine to assist with game development workflows.",
  "classification": "community",
  "weekly_metric": {
    "type": "downloads",
    "value": 24
  },
  "release_date": "Jun 4, 2025",
  "url": "https://www.pulsemcp.com/servers/runreal-unreal-engine",
  "source_url": null,
  "categories": [],
  "tags": [],
  "last_updated": null,
  "scraped_at": "2025-11-17T03:43:23.536561",
  "metadata": {}
}