{
  "id": "forwardnetworks-network-analysis",
  "name": "Forward Networks",
  "provider": "Forward Networks",
  "description": "Integrates with Forward Networks API for network topology analysis, path tracing, device management, and...",
  "classification": "official",
  "weekly_metric": null,
  "release_date": "Jun 25, 2025",
  "url": "https://www.pulsemcp.com/servers/forwardnetworks-network-analysis",
  "source_url": null,
  "categories": [],
  "tags": [],
  "last_updated": null,
  "scraped_at": "2025-11-17T03:46:51.986423",
  "metadata": {}
}