{
  "id": "mongodb-js-mongodb",
  "name": "MongoDB",
  "provider": "MongoDB Inc.",
  "description": "Provides a bridge between MongoDB databases and conversational interfaces, enabling comprehensive database...",
  "classification": "official",
  "weekly_metric": {
    "type": "visitors",
    "value": 8600
  },
  "release_date": "Apr 29, 2025",
  "url": "https://www.pulsemcp.com/servers/mongodb-js-mongodb",
  "source_url": null,
  "categories": [],
  "tags": [],
  "last_updated": null,
  "scraped_at": "2025-11-17T03:25:15.914603",
  "metadata": {}
}